infi.recipe.template.version-0.4.31-py2.7-nspkg.pth
infi/recipe/template/version/__init__.py
infi/recipe/template/version/__version__.py
infi/recipe/template/version/recipe/__init__.py
infi/recipe/template/version/recipe/default.in
infi/recipe/template/version/tests/__init__.py
infi.recipe.template.version-0.4.31.dist-info/LICENSE
infi.recipe.template.version-0.4.31.dist-info/METADATA
infi.recipe.template.version-0.4.31.dist-info/WHEEL
infi.recipe.template.version-0.4.31.dist-info/entry_points.txt
infi.recipe.template.version-0.4.31.dist-info/namespace_packages.txt
infi.recipe.template.version-0.4.31.dist-info/top_level.txt
infi.recipe.template.version-0.4.31.dist-info/RECORD
